{
  "$schema": "./node_modules/nx/schemas/workspace-schema.json",
  "version": 2,
  "projects": {
    "prices": "apps/prices",
    "prices-add-item-feature": "libs/prices/add-item/feature",
    "prices-card-feature": "libs/prices/card/feature",
    "prices-e2e": "apps/prices-e2e",
    "prices-home-feature": "libs/prices/home/feature",
    "prices-page-feature": "libs/prices/page/feature",
    "prices-shell-feature": "libs/prices/shell/feature",
    "prices-store-feature": "libs/prices/store/feature",
    "utils-common": "libs/utils-common"
  }
}
